plugnplai/__init__.py
plugnplai/api/retrieve.py
plugnplai/api_call.py
plugnplai/embeddings.py
plugnplai/plugins.py
plugnplai/prompt_templates.py
plugnplai/utils.py
plugnplai/verify_plugins/__init__.py
plugnplai/verify_plugins/verify_for_plugnplai.csv
plugnplai/verify_plugins/verify_langchain.py
plugnplai/verify_plugins/verify_plugnplai.py
plugnplai-0.0.24.dist-info/LICENSE
plugnplai-0.0.24.dist-info/METADATA
plugnplai-0.0.24.dist-info/WHEEL
plugnplai-0.0.24.dist-info/RECORD
