Metadata-Version: 2.1
Name: plugnplai
Version: 0.0.24
Summary: Connect plugins to AI
License: MIT
Requires-Python: >=3.9,<4.0
Classifier: License :: OSI Approved :: MIT License
Classifier: Programming Language :: Python :: 3
Classifier: Programming Language :: Python :: 3.9
Classifier: Programming Language :: Python :: 3.10
Classifier: Programming Language :: Python :: 3.11
Requires-Dist: faiss-cpu (>=1.7.4,<2.0.0)
Requires-Dist: jsonref (>=1.1.0,<2.0.0)
Requires-Dist: langchain (>=0.0.160,<0.0.161)
Requires-Dist: openai (>=0.27.6,<0.28.0)
Requires-Dist: pydantic (>=1.10.7,<2.0.0)
Requires-Dist: pyyaml (>=6.0,<7.0)
Requires-Dist: requests (>=2.28.2,<3.0.0)
Requires-Dist: tiktoken (>=0.3.3,<0.4.0)
